{
	"pages": [ //pages数组中第一项表示应用启动页，参考：https://uniapp.dcloud.io/collocation/pages
		{
			"path": "pages/index/index", // index
			"style": {
				"navigationStyle": "custom",
				"enablePullDownRefresh": false
			}
		}, {
			"path": "pages/login/login", // 登录和注册
			"style": {
				"navigationBarTitleText": "",
				"enablePullDownRefresh": false,
				"app-plus": {
					"titleNView": false
				}
			}

		}, {
			"path": "pages/login/uploadAvatar", // 选择头像
			"style": {
				"navigationBarTitleText": "",
				"enablePullDownRefresh": false
			}

		}, {
			"path": "pages/heart/heart", // 广场
			"style": {
				"navigationBarTitleText": "",
				"enablePullDownRefresh": false,
				"app-plus": {
					"titleNView": false,
					"scrollIndicator": "none"
					// "titleNView": {
					// 	"type": "transparent"
					// }
				}
			}
		}, {
			"path": "pages/template", // 模板页面
			"style": {
				"navigationBarTitleText": "",
				"enablePullDownRefresh": false
			}

		}, {
			"path": "pages/news/news", // 消息中心
			"style": {
				"navigationBarTitleText": "",
				"enablePullDownRefresh": false,
				"app-plus": {
					"titleNView": false
				}
			}

		}, {
			"path": "pages/user/user", // 个人中心
			"style": {
				"navigationBarTitleText": "",
				"enablePullDownRefresh": false,
				"app-plus": {
					"titleNView": false
				}
			}

		}, {
			"path": "pages/heart/details/details", // 榜单详情
			"style": {
				"navigationBarTitleText": "",
				"enablePullDownRefresh": false
			}

		}, {
			"path": "pages/user/editUserInfo/editUserInfo", // 编辑个人信息
			"style": {
				"navigationBarTitleText": "",
				"enablePullDownRefresh": false,
				"app-plus": {
					"titleNView": false
				}
			}

		}, {
			"path": "pages/user/userOrderList/userOrderList", // 我的订单
			"style": {
				"navigationBarTitleText": "",
				"enablePullDownRefresh": false,
				"app-plus": {
					"titleNView": false
				}
			}

		}, {
			"path": "pages/user/recharge/recharge", // 充值定金
			"style": {
				"navigationBarTitleText": "",
				"enablePullDownRefresh": false,
				"app-plus": {
					"titleNView": false
				}
			}

		}, {
			"path": "pages/user/pay/pay", // 支付定金
			"style": {
				"navigationBarTitleText": "",
				"enablePullDownRefresh": false,
				"app-plus": {
					"titleNView": false
				}
			}

		}, {
			"path": "pages/user/refund/refund", // 退还定金
			"style": {
				"navigationBarTitleText": "",
				"enablePullDownRefresh": false,
				"app-plus": {
					"titleNView": false
				}
			}

		}, {
			"path": "pages/user/useTime/useTime", // 充值使用时长
			"style": {
				"navigationBarTitleText": "",
				"enablePullDownRefresh": false,
				"app-plus": {
					"titleNView": false
				}
			}

		}, {
			"path": "pages/heart/mapAddress/mapAddress",
			"style": {
				"navigationBarTitleText": "",
				"enablePullDownRefresh": false
			}
		}, {
			"path": "pages/heart/searchFilter/searchFilter", // 搜索筛选
			"style": {
				"navigationBarTitleText": "",
				"enablePullDownRefresh": false,
				"app-plus": {
					"titleNView": false
				}
			}

		}, {
			"path": "pages/heart/userDetails/userDetails", // 个人详情 Nvue
			"style": {
				"navigationBarTitleText": "",
				"enablePullDownRefresh": false,
				"app-plus": {
					"titleNView": {
						"type": "transparent",
						"titleSize": "16",
						"titleColor": "#606266"
					}
					// "titleNView": false
				}

			}

		}, {
			"path": "pages/login/forgetPwd", // 忘记密码
			"style": {
				"navigationBarTitleText": "",
				"enablePullDownRefresh": false,
				"app-plus": {
					"titleNView": false
				}
			}

		}, {
			"path": "pages/user/myAttention/myAttention", // 我的关注
			"style": {
				"navigationBarTitleText": "",
				"enablePullDownRefresh": false,
				"app-plus": {
					"titleNView": false
				}
			}

		}, {
			"path": "pages/heart/searchList/searchList", // 搜索显示的员工列表
			"style": {
				"navigationBarTitleText": "",
				"enablePullDownRefresh": false,
				"app-plus": {
					"titleNView": false
				}
			}

		}, {
			"path": "pages/news/noticeInfo/noticeInfo", // 系统公告
			"style": {
				"navigationBarTitleText": "",
				"enablePullDownRefresh": false,
				"app-plus": {
					"titleNView": false
				}
			}

		}, {
			"path": "pages/list/list", // 列表
			"style": {
				"navigationBarTitleText": "",
				"enablePullDownRefresh": false,
				"app-plus": {
					"titleNView": false
				}
			}

		}, {
			"path": "pages/heart/search/search", // 搜索
			"style": {
				"navigationBarTitleText": "",
				"enablePullDownRefresh": false,
				"app-plus": {
					"titleNView": false
				}
			}

		}, {
			"path": "pages/login/register", // 注册
			"style": {
				"navigationBarTitleText": "",
				"enablePullDownRefresh": false,
				"app-plus": {
					"titleNView": false
				}
			}

		}, {
			"path": "pages/heart/evaluate/evaluate", // 评论
			"style": {
				"navigationBarTitleText": "",
				"enablePullDownRefresh": false,
				"app-plus": {
					"titleNView": false
				}
			}

		}, {
			"path": "pages/heart/timePicker/timePicker", // 时间段选择
			"style": {
				"navigationBarTitleText": "",
				"enablePullDownRefresh": false,
				"app-plus": {
					"titleNView": false
				}
			}

		}, {
			"path": "pages/heart/orderDetails/orderDetails", // 订单详情
			"style": {
				"navigationBarTitleText": "",
				"enablePullDownRefresh": false,
				"app-plus": {
					"titleNView": false
				}
			}

		}, {
			"path": "pages/heart/bookingDetails/bookingDetails", // 预约详情
			"style": {
				"navigationBarTitleText": "",
				"enablePullDownRefresh": false,
				"app-plus": {
					"titleNView": false
				}
			}

		}
	    ,{
            "path" : "pages/user/contactUs/contactUs",   // 联系我们
            "style" :                                                                                    
            {
                "navigationBarTitleText": "",
                "enablePullDownRefresh": false,
				"app-plus": {
					"titleNView": false
				}
            }
            
        }
        ,{
            "path" : "pages/heart/evaluateList/evaluateList",  // 评价列表
            "style" :                                                                                    
            {
                "navigationBarTitleText": "",
                "enablePullDownRefresh": false,
				"app-plus": {
					"titleNView": false
				}
            }
            
        }
        ,{
            "path" : "pages/user/userInfo/userInfo",  // 个人信息
            "style" :                                                                                    
            {
                "navigationBarTitleText": "",
                "enablePullDownRefresh": false,
				"app-plus": {
					"titleNView": false
				}
            }
            
        }
        ,{
            "path" : "pages/user/editPwd/editPwd", // 修改密码
            "style" :                                                                                    
            {
                "navigationBarTitleText": "",
                "enablePullDownRefresh": false,
				"app-plus": {
					"titleNView": false
				}
            }
            
        }
        ,{
            "path" : "pages/link/link",
            "style" :                                                                                    
            {
                "navigationBarTitleText": "",
                "enablePullDownRefresh": false
            }
            
        }
    ],
	"tabBar": {
		"color": "#363A3D",
		"selectedColor": "#F1598E",
		"list": [{
			"pagePath": "pages/heart/heart",
			"iconPath": "static/icon/heart.png",
			"selectedIconPath": "static/icon/heartActive.png",
			"text": "搜索"
		}, {
			"pagePath": "pages/list/list",
			"iconPath": "static/icon/list.png",
			"selectedIconPath": "static/icon/listActive.png",
			"text": "列表"
		}, {
			"pagePath": "pages/news/news",
			"iconPath": "static/icon/news.png",
			"selectedIconPath": "static/icon/newsActive.png",
			"text": "消息"
		}, {
			"pagePath": "pages/user/user",
			"iconPath": "static/icon/user.png",
			"selectedIconPath": "static/icon/userActive.png",
			"text": "我的"
		}]
	},
	"globalStyle": {
		"pageOrientation": "portrait",
		"navigationBarTextStyle": "black",
		"navigationBarBackgroundColor": "#FFFFFF",
		"backgroundColor": "#FFFFFF",
		"app-plus": {
			"scrollIndicator": "none",
			"pageOrientation": "portrait",
			"bounce": "none",
			"softinputNavBar": "none"
		}
	},
	"easycom": {
		"^u-(.*)": "uview-ui/components/u-$1/u-$1.vue"
	},
	"condition" : { //模式配置，仅开发期间生效
		"current": 0, //当前激活的模式(list 的索引项)
		"list": [
			{
				"name": "", //模式名称
				"path": "", //启动页面，必选
				"query": "" //启动参数，在页面的onLoad函数里面得到
			}
		]
	}
}
